mangadl/__init__.py
mangadl/config.py
mangadl/cli.py
mangadl/manga_dl.py
mangadl/manga.py
mangadl/scrapers/scraper.py
mangadl/scrapers/__init__.py
mangadl/scrapers/sites/__init__.py
mangadl/scrapers/sites/mangahere.py
MangaDL-0.2a1.dist-info/entry_points.txt
MangaDL-0.2a1.dist-info/METADATA
MangaDL-0.2a1.dist-info/metadata.json
MangaDL-0.2a1.dist-info/DESCRIPTION.rst
MangaDL-0.2a1.dist-info/WHEEL
MangaDL-0.2a1.dist-info/RECORD
MangaDL-0.2a1.dist-info/top_level.txt
